excel_form_builder/__init__.py
excel_form_builder/excel_to_json.py
excel_form_builder/question.py
excel_form_builder-0.1.3.data/scripts/create_form.py
excel_form_builder-0.1.3.dist-info/LICENSE
excel_form_builder-0.1.3.dist-info/METADATA
excel_form_builder-0.1.3.dist-info/WHEEL
excel_form_builder-0.1.3.dist-info/top_level.txt
excel_form_builder-0.1.3.dist-info/RECORD
