Metadata-Version: 2.1
Name: excel-form-builder
Version: 0.1.3
Summary: Convert XLSX to JSON
Home-page: UNKNOWN
Author: Anthony Seliga
Author-email: anthony.seliga@gmail.com
License: MIT
Platform: UNKNOWN
Requires-Dist: openpyxl
Requires-Dist: colorama
